{
  "number": "11209",
  "title": "所得税の更正等取消請求上告及び上告受理申立事件",
  "court": "最高裁判所",
  "date": "平成２１年５月２６日",
  "date_iso": "2009-05-26",
  "result": "取消",
  "topics": [
    "所得税"
  ],
  "laws": [],
  "keywords": [],
  "text": "\n \n 目次に戻る \n \n 判決 11209 \n 所得税の更正等取消請求上告及び上告受理申立事件 \n \n 裁判所:  最高裁判所 \n 判決日:  平成２１年５月２６日 \n 結果:  取消 \n \n \n 主文 \n 裁判官全員一致の意見で、次のとおり決定。 \n \n \n 第１ 主文 \n １ 本件上告を棄却する。\n２ 本件を上告審として受理しない。\n３ 上告費用及び申立費用は上告人兼申立人の負担とする。 \n \n \n 第２ 理由 \n １ 上告について民事事件について最高裁判所に上告をすることが許されるのは、民訴法３１２条１項又は２項所定の場合に限られるところ、本件上告理由は、違憲をいうが、その実質は事実誤認又は単なる法令違反を主張するものであって、明らかに上記各項に規定する事由に該当しない。\n２ 上告受理申立てについて本件申立ての理由によれば、本件は、民訴法３１８条１項により受理すべきものとは認められない。\n平成２１年５月２６日最高裁判所第三小法廷裁判長裁判官 藤田 宙靖裁判官 堀籠 幸男裁判官 那須 弘平裁判官 田原 睦夫裁判官 近藤 崇晴当事者目録上告人兼申立人 甲同訴訟代理人弁護士 瀬辺 勝被上告人兼相手方 桑名税務署長 藤原 忠弘同指定代理人 武藤 政男 \n \n"
}